setup.cfg
setup.py
deployme_installer.egg-info/PKG-INFO
deployme_installer.egg-info/SOURCES.txt
deployme_installer.egg-info/dependency_links.txt
deployme_installer.egg-info/entry_points.txt
deployme_installer.egg-info/not-zip-safe
deployme_installer.egg-info/requires.txt
deployme_installer.egg-info/top_level.txt
deploymeinstaller/__init__.py
scripts/deploy-install