Metadata-Version: 1.0
Name: deployme-installer
Version: 0.1dev
Summary: Simple installer for deployme
Home-page: UNKNOWN
Author: Rick Copeland
Author-email: rick@arborian.com
License: APACHE 2.0
Platform: UNKNOWN
